zblib/__init__.py
zblib-0.0.2.dist-info/LICENSE
zblib-0.0.2.dist-info/METADATA
zblib-0.0.2.dist-info/WHEEL
zblib-0.0.2.dist-info/top_level.txt
zblib-0.0.2.dist-info/RECORD
