Metadata-Version: 2.1
Name: zblib
Version: 0.0.2
Summary: private python library
Home-page: https://github.com/zbmain/py_pri
Author: zhaobin
Author-email: zbmain@qq.com
License: MIT
Platform: UNKNOWN
Classifier: Programming Language :: Python :: 3.6
Classifier: License :: OSI Approved :: MIT License
Classifier: Operating System :: OS Independent
